setup.py
stackpath/__init__.py
stackpath/stackpath.py
stackpath.egg-info/PKG-INFO
stackpath.egg-info/SOURCES.txt
stackpath.egg-info/dependency_links.txt
stackpath.egg-info/requires.txt
stackpath.egg-info/top_level.txt
test/test.py