Metadata-Version: 1.0
Name: stackpath
Version: 0.0.1
Summary: A Python REST Client for StackPath REST Web Services. This package is forked from https://github.com/MaxCDN/python-maxcdn/
Home-page: http://github.com/koty/python-stackpath
Author: Kouichi Nihsizawa
Author-email: kouichi.nishizawa+github@gmail.com
License: MIT
Keywords: StackPath CDN API REST
Platform: UNKNOWN
